ilt_panphon-0.21.3.data/scripts/align_wordlists.py
ilt_panphon-0.21.3.data/scripts/generate_ipa_all.py
ilt_panphon-0.21.3.data/scripts/validate_ipa.py
ilt_panphon-0.21.3.dist-info/licenses/LICENSE.txt
panphon/__init__.py
panphon/_panphon.py
panphon/collapse.py
panphon/distance.py
panphon/errors.py
panphon/featuretable.py
panphon/permissive.py
panphon/segment.py
panphon/sonority.py
panphon/xsampa.py
panphon/data/asjp.yml
panphon/data/diacritic_definitions.yml
panphon/data/diacritic_definitions_schema.yml
panphon/data/dolgopolsky_prime.yml
panphon/data/feature_weights.csv
panphon/data/ipa-xsampa.csv
panphon/data/ipa_all.csv
panphon/data/ipa_bases.csv
panphon/data/sort_order.yml
panphon/data/sort_order_schema.yml
ilt_panphon-0.21.3.dist-info/METADATA
ilt_panphon-0.21.3.dist-info/WHEEL
ilt_panphon-0.21.3.dist-info/top_level.txt
ilt_panphon-0.21.3.dist-info/zip-safe
ilt_panphon-0.21.3.dist-info/RECORD
