Metadata-Version: 2.4
Name: ilt-panphon
Version: 0.21.3
Summary: Tools for using the International Phonetic Alphabet with phonological features
Home-page: https://github.com/nrc-ilt/panphon
Author: David R. Mortensen
Author-email: dmortens@cs.cmu.edu
Maintainer: Eric Joanis
Maintainer-email: Eric.Joanis@nrc-cnrc.gc.ca
License: MIT
Classifier: Operating System :: OS Independent
Classifier: Programming Language :: Python :: 3
Classifier: Topic :: Software Development :: Libraries :: Python Modules
Classifier: Topic :: Text Processing :: Linguistic
Requires-Python: >=3.8.0
License-File: LICENSE.txt
Requires-Dist: setuptools<80
Requires-Dist: unicodecsv
Requires-Dist: PyYAML
Requires-Dist: regex
Requires-Dist: numpy>=1.20.2
Requires-Dist: ilt-editdistance
Requires-Dist: munkres
Dynamic: author
Dynamic: author-email
Dynamic: classifier
Dynamic: description
Dynamic: description-content-type
Dynamic: home-page
Dynamic: license
Dynamic: license-file
Dynamic: maintainer
Dynamic: maintainer-email
Dynamic: requires-dist
Dynamic: requires-python
Dynamic: summary
